{"version":1,"key":"10070","name":"A. Walton","source":"tennis-data.co.uk closing prices, mirrored to odds-archive/","priceBasis":"average closing price across books, de-vigged","note":"No opening prices exist in this source, so this is performance against the closing market, not closing line value.","minMatches":30,"overall":{"matches":49,"wins":16,"losses":33,"actualWinRate":32.7,"expectedWinRate":38.1,"vsMarket":-5.4,"ci95":[-18.1,7.3],"z":-0.84,"roi":-27.1,"roiBest":-22.8},"bySurface":{"Hard":{"matches":38,"wins":12,"losses":26,"actualWinRate":31.6,"expectedWinRate":38.8,"vsMarket":-7.3,"ci95":[-21.9,7.4],"z":-0.97,"roi":-31,"roiBest":-27}},"byRole":{"underdog":{"matches":35,"wins":7,"losses":28,"actualWinRate":20,"expectedWinRate":29.6,"vsMarket":-9.6,"ci95":[-24.2,5],"z":-1.29,"roi":-39.5,"roiBest":-35},"favourite":{"matches":14,"wins":9,"losses":5,"actualWinRate":64.3,"expectedWinRate":59.3,"vsMarket":5,"ci95":[-20.5,30.5],"z":0.38,"roi":3.9,"roiBest":7.7}},"bySeason":{"2024":{"matches":14,"wins":3,"losses":11,"actualWinRate":21.4,"expectedWinRate":41.7,"vsMarket":-20.2,"ci95":[-44.5,4.1],"z":-1.63,"roi":-55.1,"roiBest":-52},"2025":{"matches":33,"wins":13,"losses":20,"actualWinRate":39.4,"expectedWinRate":37.4,"vsMarket":2,"ci95":[-13.5,17.5],"z":0.26,"roi":-10.8,"roiBest":-5.7}}}